{
  "id": "integers",
  "label": "الأعداد الصحيحة",
  "level": 2,
  "problem": {
    "scenario": "في يوم شتائي بارد، كانت درجة الحرارة في مدينة ما تساوي $-3°C$ عند الفجر. ارتفعت الحرارة بمقدار $7$ درجات خلال النهار، ثم انخفضت $5$ درجات في الليل. ما درجة الحرارة النهائية؟",
    "hints": [
      "فكّر في مقياس الحرارة كخط أعداد: الأعداد الموجبة فوق الصفر والأعداد السالبة تحته.",
      "ابدأ من $-3$، أضف $+7$ أولاً، ثم اطرح $5$ من الناتج.",
      "$$-3 + 7 - 5 = ?$$"
    ]
  },
  "theory": {
    "sections": [
      {
        "id": "definition",
        "title": "ما هي الأعداد الصحيحة؟",
        "content": "الأعداد الصحيحة هي مجموعة تشمل الأعداد الطبيعية الموجبة $\\{1, 2, 3, ...\\}$ والصفر $\\{0\\}$ والأعداد السالبة $\\{-1, -2, -3, ...\\}$. نرمز لها بالرمز $\\mathbb{Z}$.",
        "example": "على خط الأعداد: $..., -3, -2, -1, 0, 1, 2, 3, ...$"
      },
      {
        "id": "operations",
        "title": "العمليات على الأعداد الصحيحة",
        "content": "عند جمع عددين بنفس الإشارة، نجمع القيمتين ونحتفظ بالإشارة. عند جمع عددين بإشارتين مختلفتين، نطرح القيمة الصغرى من الكبرى ونأخذ إشارة الأكبر.",
        "example": "$$(-4) + (-3) = -7$$ $$(-5) + 8 = +3$$"
      },
      {
        "id": "multiplication",
        "title": "ضرب الأعداد الصحيحة",
        "content": "موجب × موجب = موجب، سالب × سالب = موجب، موجب × سالب = سالب.",
        "example": "$$(-3) \\times (-4) = 12$$ $$5 \\times (-2) = -10$$"
      }
    ]
  },
  "mcq": {
    "question": "ما ناتج العملية التالية؟ $$(-8) + 3 - (-2)$$",
    "choices": [
      {
        "id": "a",
        "text": "$-3$"
      },
      {
        "id": "b",
        "text": "$-7$"
      },
      {
        "id": "c",
        "text": "$13$"
      },
      {
        "id": "d",
        "text": "$-13$"
      }
    ],
    "correct": "a",
    "explanation": "$$(-8) + 3 - (-2) = -8 + 3 + 2 = -3$$"
  }
}