{
  "conceptId": "pythagoras",
  "title": "نظرية فيثاغورس",
  "blocks": [
    {
      "type": "text",
      "id": "problem",
      "header": "المشكلة",
      "content": "يريد مهندس معرفة طول السلّم اللازم لبلوغ نافذة ارتفاعها $4$ أمتار، علمًا بأن قاعدة السلّم ستكون على بُعد $3$ أمتار من الجدار. ما الطول اللازم؟"
    },
    {
      "type": "text",
      "id": "theory-1",
      "header": "النظرية",
      "title": "نظرية فيثاغورس",
      "content": "في أي مثلث قائم الزاوية، مربع الوتر (الضلع المقابل للزاوية القائمة) يساوي مجموع مربعَي الضلعين الآخرين. $$c^2 = a^2 + b^2$$"
    },
    {
      "type": "text",
      "id": "theory-2",
      "title": "الثلاثيات الفيثاغورية",
      "content": "هي مجموعات من ثلاثة أعداد صحيحة تُحقّق نظرية فيثاغورس. من أشهرها: $(3,4,5)$، $(5,12,13)$، $(8,15,17)$."
    },
    {
      "type": "text",
      "id": "theory-3",
      "title": "عكس النظرية",
      "content": "إذا كانت أضلاع مثلث ثلاثة $a$، $b$، $c$ وكان $c^2 = a^2 + b^2$، فإن المثلث قائم الزاوية."
    }
  ]
}